Topsis_Kartik_102203789/102203789.py
Topsis_Kartik_102203789/__init__.py
Topsis_Kartik_102203789-1.0.0.dist-info/LICENSE
Topsis_Kartik_102203789-1.0.0.dist-info/METADATA
Topsis_Kartik_102203789-1.0.0.dist-info/WHEEL
Topsis_Kartik_102203789-1.0.0.dist-info/entry_points.txt
Topsis_Kartik_102203789-1.0.0.dist-info/top_level.txt
Topsis_Kartik_102203789-1.0.0.dist-info/RECORD
