Metadata-Version: 2.1
Name: Topsis-Kartik-102203789
Version: 1.0.0
Summary: TOPSIS implementation
Home-page: https://github.com/k-sidana-77/Topsis
Author: Kartik Sidana
Author-email: kartik.13907@gmail.com
License: UNKNOWN
Platform: UNKNOWN
Classifier: Programming Language :: Python :: 3
Classifier: License :: OSI Approved :: MIT License
Classifier: Operating System :: OS Independent
Requires-Python: >=3.6
License-File: LICENSE
Requires-Dist: numpy>=1.19.5
Requires-Dist: pandas>=1.1.5
